ngless/__init__.py
ngless/wrap.py
ngless_cwl-0.0.2.data/data/share/commonwl/ngl-types.yml
ngless_cwl-0.0.2.data/data/share/commonwl/ngless-count.cwl
ngless_cwl-0.0.2.data/data/share/commonwl/ngless-map.cwl
ngless_cwl-0.0.2.data/data/share/commonwl/ngless-mapstats.cwl
ngless_cwl-0.0.2.data/data/share/commonwl/ngless-select.cwl
ngless_cwl-0.0.2.data/data/share/commonwl/ngless-trim.cwl
ngless_cwl-0.0.2.data/data/share/commonwl/ngless-unique.cwl
ngless_cwl-0.0.2.data/data/share/commonwl/workflow-example.cwl
ngless_cwl-0.0.2.data/scripts/ngless-count.py
ngless_cwl-0.0.2.data/scripts/ngless-map.py
ngless_cwl-0.0.2.data/scripts/ngless-mapstats.py
ngless_cwl-0.0.2.data/scripts/ngless-select.py
ngless_cwl-0.0.2.data/scripts/ngless-trim.py
ngless_cwl-0.0.2.data/scripts/ngless-unique.py
ngless_cwl-0.0.2.dist-info/DESCRIPTION.rst
ngless_cwl-0.0.2.dist-info/METADATA
ngless_cwl-0.0.2.dist-info/RECORD
ngless_cwl-0.0.2.dist-info/WHEEL
ngless_cwl-0.0.2.dist-info/metadata.json
ngless_cwl-0.0.2.dist-info/top_level.txt
