Metadata-Version: 2.0
Name: ngless-cwl
Version: 0.0.2
Summary: ngless wrappers for common operations and use with CWL workflows
Home-page: https://github.com/luispedro/NGLess
Author: NGLess team
Author-email: ngless@googlegroups.com
License: MIT
Platform: any
Classifier: Development Status :: 4 - Beta
Classifier: Intended Audience :: Developers
Classifier: License :: OSI Approved :: MIT License
Classifier: Operating System :: OS Independent
Classifier: Programming Language :: Python :: 2
Classifier: Topic :: Scientific/Engineering :: Bio-Informatics
Classifier: Topic :: Software Development :: Libraries :: Python Modules
